chewBBACA_NServer-1.0.4.dist-info/top_level.txt
chewBBACA_NServer-1.0.4.dist-info/RECORD
chewBBACA_NServer-1.0.4.dist-info/DESCRIPTION.rst
chewBBACA_NServer-1.0.4.dist-info/WHEEL
chewBBACA_NServer-1.0.4.dist-info/METADATA
chewBBACA_NServer-1.0.4.dist-info/metadata.json
chewBBACA_NServer-1.0.4.dist-info/entry_points.txt
CHEWBBACA_NS/chewBBACA.py
CHEWBBACA_NS/__init__.py
CHEWBBACA_NS/utils/TestGenomeQuality.py
CHEWBBACA_NS/utils/init_schema_4_bbaca.py
CHEWBBACA_NS/utils/RemoveGenomes.py
CHEWBBACA_NS/utils/profile_joiner.py
CHEWBBACA_NS/utils/calc_bsr_short.py
CHEWBBACA_NS/utils/__init__.py
CHEWBBACA_NS/utils/down_profiles.py
CHEWBBACA_NS/utils/sync_schema.py
CHEWBBACA_NS/utils/send2NS.py
CHEWBBACA_NS/utils/send_metadata.py
CHEWBBACA_NS/utils/CountNumberMissingData.py
CHEWBBACA_NS/utils/ParalogPrunning.py
CHEWBBACA_NS/utils/Extract_cgAlleles.py
CHEWBBACA_NS/utils/RemoveGenes.py
CHEWBBACA_NS/utils/AutoAlleleCuration.py
CHEWBBACA_NS/utils/CommonFastaFunctions.py
CHEWBBACA_NS/utils/down_schema.py
CHEWBBACA_NS/allelecall/callAlleles_protein3.py
CHEWBBACA_NS/allelecall/CommonFastaFunctions.py
CHEWBBACA_NS/allelecall/BBACA.py
CHEWBBACA_NS/allelecall/runProdigal.py
CHEWBBACA_NS/allelecall/Create_Genome_Blastdb.py
CHEWBBACA_NS/SchemaEvaluator/__init__.py
CHEWBBACA_NS/SchemaEvaluator/alleleSizeStats.py
CHEWBBACA_NS/SchemaEvaluator/CheckCDS.py
CHEWBBACA_NS/SchemaEvaluator/ValidateSchema.py
